unlearning/__init__.py
unlearning-0.0.1.dist-info/LICENSE
unlearning-0.0.1.dist-info/METADATA
unlearning-0.0.1.dist-info/WHEEL
unlearning-0.0.1.dist-info/top_level.txt
unlearning-0.0.1.dist-info/RECORD
